<?xml version="1.0"?>
<!--
/**
 * Webkul Software.
 *
 * @category  Webkul
 * @package   Webkul_GiftCard
 * @author    Webkul
 * @copyright Copyright (c) Webkul Software Private Limited (https://webkul.com)
 * @license   https://store.webkul.com/license.html
 */
-->
<page xmlns:xsi="http://www.w3.org/2001/XMLSchema-instance" xsi:noNamespaceSchemaLocation="urn:magento:framework:View/Layout/etc/page_configuration.xsd">
    <update handle="customer_account"/>
    <head>
        <css src="Webkul_GiftCard::css/style.css" />
	</head>
    <body>
        <referenceContainer name="content">
            <block class="Webkul\GiftCard\Block\Detail" name="webkul_giftcard_giftuser_list" template="Webkul_GiftCard::giftcard/detail.phtml" cacheable="false">
            </block>
        </referenceContainer>
    </body>
</page>
